graphlib2-0.4.7.dist-info/METADATA
graphlib2-0.4.7.dist-info/WHEEL
graphlib2-0.4.7.dist-info/license_files/LICENSE.txt
graphlib2/_types.py
graphlib2/_graphlib2.pyi
graphlib2/__init__.py
graphlib2/py.typed
graphlib2/_graphlib2.pypy39-pp73-darwin.so
graphlib2-0.4.7.dist-info/RECORD
