Metadata-Version: 2.1
Name: graphlib2
Version: 0.4.7
Classifier: Development Status :: 3 - Alpha
Classifier: Intended Audience :: Developers
Classifier: License :: OSI Approved :: MIT License
Classifier: Topic :: Software Development
Classifier: Topic :: Software Development :: Libraries
Classifier: Topic :: Software Development :: Libraries :: Python Modules
Requires-Dist: typing-extensions>=3; python_version < '3.8'
License-File: LICENSE.txt
Summary: Rust port of the Python stdlib graphlib modules
Author: Adrian Garcia Badaracco
License: MIT
Requires-Python: >=3.7
Project-URL: repository, https://github.com/adriangb/graphlib2
Project-URL: homepage, https://github.com/adriangb/graphlib2
Project-URL: documentation, https://github.com/adriangb/graphlib2/README.md
